igfold_pytorch/__init__.py
igfold_pytorch/igfold_pytorch.py
igfold_pytorch-0.0.2.dist-info/METADATA
igfold_pytorch-0.0.2.dist-info/WHEEL
igfold_pytorch-0.0.2.dist-info/top_level.txt
igfold_pytorch-0.0.2.dist-info/RECORD
