Metadata-Version: 2.1
Name: igfold-pytorch
Version: 0.0.2
Summary: IgFold - Pytorch
Home-page: https://github.com/dohlee/igfold-pytorch
Author: Dohoon Lee
Author-email: dohlee.bioinfo@gmail.com
License: MIT
Keywords: artificial intelligence,protein structure prediction
Classifier: Development Status :: 4 - Beta
Classifier: Intended Audience :: Developers
Classifier: Topic :: Scientific/Engineering :: Artificial Intelligence
Classifier: License :: OSI Approved :: MIT License
Classifier: Programming Language :: Python :: 3.9
Requires-Dist: einops (>=0.3)
Requires-Dist: numpy
Requires-Dist: torch (>=1.6)
